slacker_log_handler/__init__.py
slacker_log_handler-1.2.0.dist-info/DESCRIPTION.rst
slacker_log_handler-1.2.0.dist-info/METADATA
slacker_log_handler-1.2.0.dist-info/RECORD
slacker_log_handler-1.2.0.dist-info/WHEEL
slacker_log_handler-1.2.0.dist-info/metadata.json
slacker_log_handler-1.2.0.dist-info/top_level.txt
