Metadata-Version: 2.0
Name: slacker-log-handler
Version: 1.2.0
Summary: Posts log events to Slack via API
Home-page: https://github.com/mathiasose/slacker_log_handler
Author: Mathias Ose
Author-email: mathias.ose@gmail.com
License: UNKNOWN
Download-URL: https://github.com/mathiasose/slacker_log_handler/tarball/1.2.0
Keywords: slack,logging
Platform: UNKNOWN
Classifier: Development Status :: 5 - Production/Stable
Classifier: Environment :: Web Environment
Classifier: Framework :: Django
Classifier: Intended Audience :: Developers
Classifier: Intended Audience :: System Administrators
Classifier: License :: OSI Approved :: Apache Software License
Classifier: Natural Language :: English
Classifier: Operating System :: OS Independent
Classifier: Programming Language :: Python
Classifier: Programming Language :: Python :: 2
Classifier: Programming Language :: Python :: 3
Classifier: Topic :: Communications :: Chat
Classifier: Topic :: Office/Business :: Groupware
Requires-Dist: slacker (>=0.7.3,<=0.9.9)
